hexdutils/__init__.py
hexdutils-1.2.dist-info/METADATA
hexdutils-1.2.dist-info/RECORD
hexdutils-1.2.dist-info/WHEEL
hexdutils-1.2.dist-info/top_level.txt
