Metadata-Version: 2.1
Name: hexdutils
Version: 1.2
Summary: Python library to deal with hexadecimals
Home-page: https://github.com/davix3f/hexutils
Author: davix3f
Author-email: davide_fiorito@libero.it
License: UNKNOWN
Platform: UNKNOWN
